sqlalchemy_tibero/__init__.py
sqlalchemy_tibero/base.py
sqlalchemy_tibero/provision.py
sqlalchemy_tibero/pyodbc.py
sqlalchemy_tibero/requirements.py
sqlalchemy_tibero-1.4.56.dist-info/licenses/LICENSE
sqlalchemy_tibero-1.4.56.dist-info/METADATA
sqlalchemy_tibero-1.4.56.dist-info/WHEEL
sqlalchemy_tibero-1.4.56.dist-info/entry_points.txt
sqlalchemy_tibero-1.4.56.dist-info/top_level.txt
sqlalchemy_tibero-1.4.56.dist-info/RECORD
