Metadata-Version: 2.4
Name: sqlalchemy-tibero
Version: 1.4.56
Summary: SQLAlchemy Tibero Dialect
Home-page: https://github.com/ybjeon01/sqlalchemy-tibero
Author: Yeongbae Jeon
Author-email: ybjeon01@naver.com
License: MIT
Project-URL: Documentation, https://github.com/ybjeon01/sqlalchemy-tibero/wiki
Project-URL: Source, https://github.com/ybjeon01/sqlalchemy-tibero
Project-URL: Tracker, https://github.com/ybjeon01/sqlalchemy-tibero/issues
Keywords: SQLAlchemy,Tibero
Classifier: Development Status :: 3 - Alpha
Classifier: Intended Audience :: Developers
Classifier: License :: OSI Approved :: MIT License
Classifier: Operating System :: OS Independent
Classifier: Programming Language :: Python
Classifier: Programming Language :: Python :: 3
Classifier: Programming Language :: Python :: 3.8
Classifier: Programming Language :: Python :: 3.9
Classifier: Programming Language :: Python :: 3.10
Classifier: Programming Language :: Python :: 3.11
Classifier: Programming Language :: Python :: 3.12
Classifier: Programming Language :: Python :: 3.13
Classifier: Programming Language :: Python :: 3.14
Classifier: Programming Language :: Python :: Implementation :: CPython
Classifier: Programming Language :: Python :: Implementation :: PyPy
Classifier: Topic :: Database :: Front-Ends
Requires-Python: >=3.8
License-File: LICENSE
Requires-Dist: SQLAlchemy<2,>=1
Provides-Extra: dev
Requires-Dist: ruff; extra == "dev"
Requires-Dist: mypy; extra == "dev"
Requires-Dist: pre-commit; extra == "dev"
Requires-Dist: tox; extra == "dev"
Requires-Dist: pytest; extra == "dev"
Requires-Dist: setuptools; extra == "dev"
Requires-Dist: twine; extra == "dev"
Provides-Extra: pyodbc
Requires-Dist: pyodbc>=5; extra == "pyodbc"
Dynamic: license-file
